odoo/addons/kpi_data_hub/MIGRATION_TO_16.md
odoo/addons/kpi_data_hub/MIS_INTEGRATION_README.md
odoo/addons/kpi_data_hub/README.md
odoo/addons/kpi_data_hub/TECHNICAL_GUIDE.md
odoo/addons/kpi_data_hub/USER_GUIDE.es.md
odoo/addons/kpi_data_hub/__init__.py
odoo/addons/kpi_data_hub/__manifest__.py
odoo/addons/kpi_data_hub/controllers/__init__.py
odoo/addons/kpi_data_hub/data/force_register_aep.xml
odoo/addons/kpi_data_hub/data/kpi_data_record_sequence.xml
odoo/addons/kpi_data_hub/data/post_install_data.xml
odoo/addons/kpi_data_hub/demo/__init__.py
odoo/addons/kpi_data_hub/demo/balance_template_demo.xml
odoo/addons/kpi_data_hub/demo/comprehensive_demo.xml
odoo/addons/kpi_data_hub/demo/demo_config.xml
odoo/addons/kpi_data_hub/demo/demo_data.xml
odoo/addons/kpi_data_hub/demo/demo_scenarios.xml
odoo/addons/kpi_data_hub/demo/hybrid_mis_report_demo.xml
odoo/addons/kpi_data_hub/demo/kpi_data_hub_demo.xml
odoo/addons/kpi_data_hub/demo/mis_reports_demo.xml
odoo/addons/kpi_data_hub/demo/quick_start_examples.md
odoo/addons/kpi_data_hub/demo/simple_demo.xml
odoo/addons/kpi_data_hub/migrations/16.0.1.1.0/pre-migration.py
odoo/addons/kpi_data_hub/models/__init__.py
odoo/addons/kpi_data_hub/models/kpi_data_record.py
odoo/addons/kpi_data_hub/models/kpi_data_template.py
odoo/addons/kpi_data_hub/models/kpi_entity.py
odoo/addons/kpi_data_hub/models/kpi_hub_aep_source.py
odoo/addons/kpi_data_hub/models/mis_aep_extension.py
odoo/addons/kpi_data_hub/models/mis_kpi_data_integration.py
odoo/addons/kpi_data_hub/models/post_install.py
odoo/addons/kpi_data_hub/reports/__init__.py
odoo/addons/kpi_data_hub/security/ir.model.access.csv
odoo/addons/kpi_data_hub/security/kpi_data_hub_security.xml
odoo/addons/kpi_data_hub/tests/__init__.py
odoo/addons/kpi_data_hub/tests/test_item_value_deletion.py
odoo/addons/kpi_data_hub/views/__init__.py
odoo/addons/kpi_data_hub/views/kpi_data_record_views.xml
odoo/addons/kpi_data_hub/views/kpi_data_template_views.xml
odoo_addon_kpi_data_hub-16.0.1.1.1.dist-info/METADATA
odoo_addon_kpi_data_hub-16.0.1.1.1.dist-info/WHEEL
odoo_addon_kpi_data_hub-16.0.1.1.1.dist-info/top_level.txt
odoo_addon_kpi_data_hub-16.0.1.1.1.dist-info/RECORD
