Metadata-Version: 2.1
Name: odoo-addon-kpi-data-hub
Version: 16.0.1.1.1
Summary: A module to store and manage KPI data for reporting.
Home-page: 
Author: nicolasramos
License: LGPL-3
Classifier: Programming Language :: Python
Classifier: Framework :: Odoo
Classifier: Framework :: Odoo :: 16.0
Classifier: License :: OSI Approved :: GNU Lesser General Public License v3 (LGPLv3)
Requires-Python: >=3.10
Requires-Dist: odoo-addon-date-range<16.1dev,>=16.0dev
Requires-Dist: odoo-addon-mis-builder<16.1dev,>=16.0dev
Requires-Dist: odoo<16.1dev,>=16.0a
